legomena.py
legomena-1.2.0.dist-info/LICENSE
legomena-1.2.0.dist-info/METADATA
legomena-1.2.0.dist-info/WHEEL
legomena-1.2.0.dist-info/top_level.txt
legomena-1.2.0.dist-info/RECORD
