Metadata-Version: 2.1
Name: legomena
Version: 1.2.0
Summary: Tool for exploring types, tokens, and n-legomena relationships in text.
Home-page: https://github.com/VictorDavis/legomena
Author: Victor Davis
Author-email: vadsql@gmail.com
License: MIT
Platform: UNKNOWN
Requires-Python: >=3.5
Requires-Dist: mpmath
Requires-Dist: nltk
Requires-Dist: numpy
Requires-Dist: pandas
Requires-Dist: scipy
